{
    "kind": "youtube#searchListResponse",
    "etag": "V8WVnRBpQ4xp1sZk1wEJlvZ5gfE",
    "nextPageToken": "CJYBEAA",
    "prevPageToken": "CGQQAQ",
    "regionCode": "PH",
    "pageInfo": {
      "totalResults": 36748,
      "resultsPerPage": 50
    },
    "items": [
      {
        "kind": "youtube#searchResult",
        "etag": "b8THTE6_-QS4yGuJ1dSaSz_DwYA",
        "id": {
          "kind": "youtube#video",
          "videoId": "G1T4UekSwEY"
        },
        "snippet": {
          "publishedAt": "2021-03-25T04:21:50Z",
          "channelId": "UCWJ2lWNubArHWmf3FIHbfcQ",
          "title": "NETS at JAZZ | FULL GAME HIGHLIGHTS | March 24, 2021",
          "description": "NETS at JAZZ | FULL GAME HIGHLIGHTS | March 24, 2021 The Utah Jazz defeated the Brooklyn Nets, 118-88. Donovan Mitchell led the way for the Jazz with ...",
          "thumbnails": {
            "default": {
              "url": "https://i.ytimg.com/vi/G1T4UekSwEY/default.jpg",
              "width": 120,
              "height": 90
            },
            "medium": {
              "url": "https://i.ytimg.com/vi/G1T4UekSwEY/mqdefault.jpg",
              "width": 320,
              "height": 180
            },
            "high": {
              "url": "https://i.ytimg.com/vi/G1T4UekSwEY/hqdefault.jpg",
              "width": 480,
              "height": 360
            }
          },
          "channelTitle": "NBA",
          "liveBroadcastContent": "none",
          "publishTime": "2021-03-25T04:21:50Z"
        }
      },
      {
        "kind": "youtube#searchResult",
        "etag": "5IFWC3lq6i029BEUphc4deFIi9k",
        "id": {
          "kind": "youtube#video",
          "videoId": "35_ozrp9Rrw"
        },
        "snippet": {
          "publishedAt": "2021-04-27T01:27:06Z",
          "channelId": "UCWJ2lWNubArHWmf3FIHbfcQ",
          "title": "THUNDER at 76ERS | FULL GAME HIGHLIGHTS | April 26, 2021",
          "description": "THUNDER at 76ERS | FULL GAME HIGHLIGHTS | April 26, 2021 The Philadelphia 76ers defeated the Oklahoma City Thunder, 121-90. Joel Embiid recorded a ...",
          "thumbnails": {
            "default": {
              "url": "https://i.ytimg.com/vi/35_ozrp9Rrw/default.jpg",
              "width": 120,
              "height": 90
            },
            "medium": {
              "url": "https://i.ytimg.com/vi/35_ozrp9Rrw/mqdefault.jpg",
              "width": 320,
              "height": 180
            },
            "high": {
              "url": "https://i.ytimg.com/vi/35_ozrp9Rrw/hqdefault.jpg",
              "width": 480,
              "height": 360
            }
          },
          "channelTitle": "NBA",
          "liveBroadcastContent": "none",
          "publishTime": "2021-04-27T01:27:06Z"
        }
      },
      {
        "kind": "youtube#searchResult",
        "etag": "hp_Q1lqOvhViHGMrR7LSzmEapGE",
        "id": {
          "kind": "youtube#video",
          "videoId": "La94GusemBs"
        },
        "snippet": {
          "publishedAt": "2021-03-31T03:20:58Z",
          "channelId": "UCWJ2lWNubArHWmf3FIHbfcQ",
          "title": "76ERS at NUGGETS | FULL GAME HIGHLIGHTS | March 30, 2021",
          "description": "76ERS at NUGGETS | FULL GAME HIGHLIGHTS | March 30, 2021 Jamal Murray (30 PTS) and Michael Porter Jr. (27 PTS, 12 REB) have combined for 57 PTS ...",
          "thumbnails": {
            "default": {
              "url": "https://i.ytimg.com/vi/La94GusemBs/default.jpg",
              "width": 120,
              "height": 90
            },
            "medium": {
              "url": "https://i.ytimg.com/vi/La94GusemBs/mqdefault.jpg",
              "width": 320,
              "height": 180
            },
            "high": {
              "url": "https://i.ytimg.com/vi/La94GusemBs/hqdefault.jpg",
              "width": 480,
              "height": 360
            }
          },
          "channelTitle": "NBA",
          "liveBroadcastContent": "none",
          "publishTime": "2021-03-31T03:20:58Z"
        }
      },
      {
        "kind": "youtube#searchResult",
        "etag": "WjarJtCyZ4iW1-TuOvdiN6QtylQ",
        "id": {
          "kind": "youtube#video",
          "videoId": "Cy4mDIjk2pM"
        },
        "snippet": {
          "publishedAt": "2021-04-14T02:05:50Z",
          "channelId": "UCWJ2lWNubArHWmf3FIHbfcQ",
          "title": "CLIPPERS at PACERS | FULL GAME HIGHLIGHTS | April 13, 2021",
          "description": "CLIPPERS at PACERS | FULL GAME HIGHLIGHTS | April 13, 2021 Led by Paul George's 36 PTS, 7 REB and 8 AST, the LA Clippers defeated the Indiana ...",
          "thumbnails": {
            "default": {
              "url": "https://i.ytimg.com/vi/Cy4mDIjk2pM/default.jpg",
              "width": 120,
              "height": 90
            },
            "medium": {
              "url": "https://i.ytimg.com/vi/Cy4mDIjk2pM/mqdefault.jpg",
              "width": 320,
              "height": 180
            },
            "high": {
              "url": "https://i.ytimg.com/vi/Cy4mDIjk2pM/hqdefault.jpg",
              "width": 480,
              "height": 360
            }
          },
          "channelTitle": "NBA",
          "liveBroadcastContent": "none",
          "publishTime": "2021-04-14T02:05:50Z"
        }
      },
      {
        "kind": "youtube#searchResult",
        "etag": "PPyld_FqDbFywJXsph1AK63JQlw",
        "id": {
          "kind": "youtube#video",
          "videoId": "AV44REfKrwE"
        },
        "snippet": {
          "publishedAt": "2021-04-24T04:30:39Z",
          "channelId": "UCWJ2lWNubArHWmf3FIHbfcQ",
          "title": "GRIZZLIES at BLAZERS | FULL GAME HIGHLIGHTS | April 23, 2021",
          "description": "GRIZZLIES at BLAZERS | FULL GAME HIGHLIGHTS | April 23, 2021 Led by Ja Morant's 33 PTS (11-17 FG), 5 REB and season-high 13 AST, the Memphis ...",
          "thumbnails": {
            "default": {
              "url": "https://i.ytimg.com/vi/AV44REfKrwE/default.jpg",
              "width": 120,
              "height": 90
            },
            "medium": {
              "url": "https://i.ytimg.com/vi/AV44REfKrwE/mqdefault.jpg",
              "width": 320,
              "height": 180
            },
            "high": {
              "url": "https://i.ytimg.com/vi/AV44REfKrwE/hqdefault.jpg",
              "width": 480,
              "height": 360
            }
          },
          "channelTitle": "NBA",
          "liveBroadcastContent": "none",
          "publishTime": "2021-04-24T04:30:39Z"
        }
      },
      {
        "kind": "youtube#searchResult",
        "etag": "waFmcui_XDxNAzKG-1G6LGxk8L8",
        "id": {
          "kind": "youtube#video",
          "videoId": "1rDNYMBnC2k"
        },
        "snippet": {
          "publishedAt": "2021-04-01T02:39:08Z",
          "channelId": "UCWJ2lWNubArHWmf3FIHbfcQ",
          "title": "JAZZ at GRIZZLIES | FULL GAME HIGHLIGHTS | March 31, 2021",
          "description": "JAZZ at GRIZZLIES | FULL GAME HIGHLIGHTS | March 31, 2021 The Utah Jazz defeated the Memphis Grizzlies, 111-107. Mike Conley recorded 26 PTS (13 ...",
          "thumbnails": {
            "default": {
              "url": "https://i.ytimg.com/vi/1rDNYMBnC2k/default.jpg",
              "width": 120,
              "height": 90
            },
            "medium": {
              "url": "https://i.ytimg.com/vi/1rDNYMBnC2k/mqdefault.jpg",
              "width": 320,
              "height": 180
            },
            "high": {
              "url": "https://i.ytimg.com/vi/1rDNYMBnC2k/hqdefault.jpg",
              "width": 480,
              "height": 360
            }
          },
          "channelTitle": "NBA",
          "liveBroadcastContent": "none",
          "publishTime": "2021-04-01T02:39:08Z"
        }
      },
      {
        "kind": "youtube#searchResult",
        "etag": "ZfeEB3uP7QLdGvaTTv0HEUIj7OA",
        "id": {
          "kind": "youtube#video",
          "videoId": "rDm6C5kkFgk"
        },
        "snippet": {
          "publishedAt": "2021-04-10T02:35:15Z",
          "channelId": "UCWJ2lWNubArHWmf3FIHbfcQ",
          "title": "76ERS at PELICANS | FULL GAME HIGHLIGHTS | April 9, 2021",
          "description": "76ERS at PELICANS | FULL GAME HIGHLIGHTS | April 9, 2021 0:00 - 1Q 2:13 - 2Q 4:33 - 3Q 6:29 - 4Q Subscribe to the NBA: https://on.nba.com/2JX5gSN Full ...",
          "thumbnails": {
            "default": {
              "url": "https://i.ytimg.com/vi/rDm6C5kkFgk/default.jpg",
              "width": 120,
              "height": 90
            },
            "medium": {
              "url": "https://i.ytimg.com/vi/rDm6C5kkFgk/mqdefault.jpg",
              "width": 320,
              "height": 180
            },
            "high": {
              "url": "https://i.ytimg.com/vi/rDm6C5kkFgk/hqdefault.jpg",
              "width": 480,
              "height": 360
            }
          },
          "channelTitle": "NBA",
          "liveBroadcastContent": "none",
          "publishTime": "2021-04-10T02:35:15Z"
        }
      },
      {
        "kind": "youtube#searchResult",
        "etag": "g0LAUR1mVI9InJBvkXpLEEeJZ8A",
        "id": {
          "kind": "youtube#video",
          "videoId": "Do80SRu93uo"
        },
        "snippet": {
          "publishedAt": "2021-04-14T06:39:10Z",
          "channelId": "UCWJ2lWNubArHWmf3FIHbfcQ",
          "title": "NBA Top 10 Plays Of The Night | April 13, 2021",
          "description": "Check out the top 10 plays of the night from April 13 featuring Aaron Holiday, Paul George and MORE! 0:00\u200b\u200b\u200b\u200b\u200b\u200b - 10 | Donovan Mitchell 0:16\u200b\u200b\u200b - 9 ...",
          "thumbnails": {
            "default": {
              "url": "https://i.ytimg.com/vi/Do80SRu93uo/default.jpg",
              "width": 120,
              "height": 90
            },
            "medium": {
              "url": "https://i.ytimg.com/vi/Do80SRu93uo/mqdefault.jpg",
              "width": 320,
              "height": 180
            },
            "high": {
              "url": "https://i.ytimg.com/vi/Do80SRu93uo/hqdefault.jpg",
              "width": 480,
              "height": 360
            }
          },
          "channelTitle": "NBA",
          "liveBroadcastContent": "none",
          "publishTime": "2021-04-14T06:39:10Z"
        }
      },
      {
        "kind": "youtube#searchResult",
        "etag": "8birvzNNVlPE0KiBk66kil82-78",
        "id": {
          "kind": "youtube#video",
          "videoId": "SowXsndTVvY"
        },
        "snippet": {
          "publishedAt": "2021-03-24T04:54:52Z",
          "channelId": "UCWJ2lWNubArHWmf3FIHbfcQ",
          "title": "76ERS at WARRIORS | FULL GAME HIGHLIGHTS | March 23, 2021",
          "description": "76ERS at WARRIORS | FULL GAME HIGHLIGHTS | March 23, 2021 The Philadelphia 76ers defeated the Golden State Warriors, 108-98. Tobias Harris recorded ...",
          "thumbnails": {
            "default": {
              "url": "https://i.ytimg.com/vi/SowXsndTVvY/default.jpg",
              "width": 120,
              "height": 90
            },
            "medium": {
              "url": "https://i.ytimg.com/vi/SowXsndTVvY/mqdefault.jpg",
              "width": 320,
              "height": 180
            },
            "high": {
              "url": "https://i.ytimg.com/vi/SowXsndTVvY/hqdefault.jpg",
              "width": 480,
              "height": 360
            }
          },
          "channelTitle": "NBA",
          "liveBroadcastContent": "none",
          "publishTime": "2021-03-24T04:54:52Z"
        }
      },
      {
        "kind": "youtube#searchResult",
        "etag": "qbZe5GqVW8NurMcYRezg6GoPorI",
        "id": {
          "kind": "youtube#video",
          "videoId": "bM18drca8_k"
        },
        "snippet": {
          "publishedAt": "2021-02-16T05:36:04Z",
          "channelId": "UCWJ2lWNubArHWmf3FIHbfcQ",
          "title": "CAVALIERS at WARRIORS | FULL GAME HIGHLIGHTS | February 15, 2021",
          "description": "CAVALIERS at WARRIORS | FULL GAME HIGHLIGHTS | February 15, 2021 The Golden State Warriors defeated the Cleveland Cavaliers, 129-98. Stephen ...",
          "thumbnails": {
            "default": {
              "url": "https://i.ytimg.com/vi/bM18drca8_k/default.jpg",
              "width": 120,
              "height": 90
            },
            "medium": {
              "url": "https://i.ytimg.com/vi/bM18drca8_k/mqdefault.jpg",
              "width": 320,
              "height": 180
            },
            "high": {
              "url": "https://i.ytimg.com/vi/bM18drca8_k/hqdefault.jpg",
              "width": 480,
              "height": 360
            }
          },
          "channelTitle": "NBA",
          "liveBroadcastContent": "none",
          "publishTime": "2021-02-16T05:36:04Z"
        }
      },
      {
        "kind": "youtube#searchResult",
        "etag": "vN-EziqoDWu07ZymCuYd4DM4y2s",
        "id": {
          "kind": "youtube#video",
          "videoId": "n8etBbsGOow"
        },
        "snippet": {
          "publishedAt": "2021-03-15T03:28:44Z",
          "channelId": "UCWJ2lWNubArHWmf3FIHbfcQ",
          "title": "CLIPPERS at PELICANS | FULL GAME HIGHLIGHTS | March 14, 2021",
          "description": "CLIPPERS at PELICANS | FULL GAME HIGHLIGHTS | March 14, 2021 The New Orleans Pelicans defeated the LA Clippers, 135-115. Zion Williamson (27 PTS, ...",
          "thumbnails": {
            "default": {
              "url": "https://i.ytimg.com/vi/n8etBbsGOow/default.jpg",
              "width": 120,
              "height": 90
            },
            "medium": {
              "url": "https://i.ytimg.com/vi/n8etBbsGOow/mqdefault.jpg",
              "width": 320,
              "height": 180
            },
            "high": {
              "url": "https://i.ytimg.com/vi/n8etBbsGOow/hqdefault.jpg",
              "width": 480,
              "height": 360
            }
          },
          "channelTitle": "NBA",
          "liveBroadcastContent": "none",
          "publishTime": "2021-03-15T03:28:44Z"
        }
      },
      {
        "kind": "youtube#searchResult",
        "etag": "3StWIJKqXxU_V60bexMdkZ9hKZM",
        "id": {
          "kind": "youtube#video",
          "videoId": "S8RR_9-HTfI"
        },
        "snippet": {
          "publishedAt": "2021-04-21T06:58:41Z",
          "channelId": "UCWJ2lWNubArHWmf3FIHbfcQ",
          "title": "NBA Top 5 Plays Of The Night | April 20, 2021",
          "description": "Check out the top 5 plays of the night from April 20 featuring Anthony Edwards, Jeff Green, and MORE! 0:00 - 5 | Rajon Rondo 0:18\u200b\u200b\u200b\u200b - 4 | Immanuel ...",
          "thumbnails": {
            "default": {
              "url": "https://i.ytimg.com/vi/S8RR_9-HTfI/default.jpg",
              "width": 120,
              "height": 90
            },
            "medium": {
              "url": "https://i.ytimg.com/vi/S8RR_9-HTfI/mqdefault.jpg",
              "width": 320,
              "height": 180
            },
            "high": {
              "url": "https://i.ytimg.com/vi/S8RR_9-HTfI/hqdefault.jpg",
              "width": 480,
              "height": 360
            }
          },
          "channelTitle": "NBA",
          "liveBroadcastContent": "none",
          "publishTime": "2021-04-21T06:58:41Z"
        }
      },
      {
        "kind": "youtube#searchResult",
        "etag": "F3iRbl57CceCgX-lnnpkP2QN9OU",
        "id": {
          "kind": "youtube#video",
          "videoId": "MkRZX9u6FAA"
        },
        "snippet": {
          "publishedAt": "2021-04-14T04:46:14Z",
          "channelId": "UCWJ2lWNubArHWmf3FIHbfcQ",
          "title": "CELTICS at TRAIL BLAZERS | FULL GAME HIGHLIGHTS | April 13, 2021",
          "description": "CELTICS at TRAIL BLAZERS | FULL GAME HIGHLIGHTS | April 13, 2021 The Boston Celtics defeated the Portland Trail Blazers, 116-115. Jayson Tatum led the ...",
          "thumbnails": {
            "default": {
              "url": "https://i.ytimg.com/vi/MkRZX9u6FAA/default.jpg",
              "width": 120,
              "height": 90
            },
            "medium": {
              "url": "https://i.ytimg.com/vi/MkRZX9u6FAA/mqdefault.jpg",
              "width": 320,
              "height": 180
            },
            "high": {
              "url": "https://i.ytimg.com/vi/MkRZX9u6FAA/hqdefault.jpg",
              "width": 480,
              "height": 360
            }
          },
          "channelTitle": "NBA",
          "liveBroadcastContent": "none",
          "publishTime": "2021-04-14T04:46:14Z"
        }
      },
      {
        "kind": "youtube#searchResult",
        "etag": "ASv9L-8jId1zGZH5wBpJBXPYJvw",
        "id": {
          "kind": "youtube#video",
          "videoId": "hOAD7HkmUCE"
        },
        "snippet": {
          "publishedAt": "2021-03-23T04:23:57Z",
          "channelId": "UCWJ2lWNubArHWmf3FIHbfcQ",
          "title": "HAWKS at CLIPPERS | FULL GAME HIGHLIGHTS | March 22, 2021",
          "description": "HAWKS at CLIPPERS | FULL GAME HIGHLIGHTS | March 22, 2021 The LA Clippers overcame a 22-point deficit to defeat the Atlanta Hawks, 119-110.",
          "thumbnails": {
            "default": {
              "url": "https://i.ytimg.com/vi/hOAD7HkmUCE/default.jpg",
              "width": 120,
              "height": 90
            },
            "medium": {
              "url": "https://i.ytimg.com/vi/hOAD7HkmUCE/mqdefault.jpg",
              "width": 320,
              "height": 180
            },
            "high": {
              "url": "https://i.ytimg.com/vi/hOAD7HkmUCE/hqdefault.jpg",
              "width": 480,
              "height": 360
            }
          },
          "channelTitle": "NBA",
          "liveBroadcastContent": "none",
          "publishTime": "2021-03-23T04:23:57Z"
        }
      },
      {
        "kind": "youtube#searchResult",
        "etag": "9qCVUnc_E1kH9VTLtm15WL0j9M0",
        "id": {
          "kind": "youtube#video",
          "videoId": "0fI6TZmfiqU"
        },
        "snippet": {
          "publishedAt": "2021-04-24T01:55:33Z",
          "channelId": "UCWJ2lWNubArHWmf3FIHbfcQ",
          "title": "HEAT at HAWKS | FULL GAME HIGHLIGHTS | April 23, 2021",
          "description": "HEAT at HAWKS | FULL GAME HIGHLIGHTS | April 23, 2021 The Atlanta Hawks defeated the Miami Heat, 118-103. Bogdan Bogdanovic recorded a team-high ...",
          "thumbnails": {
            "default": {
              "url": "https://i.ytimg.com/vi/0fI6TZmfiqU/default.jpg",
              "width": 120,
              "height": 90
            },
            "medium": {
              "url": "https://i.ytimg.com/vi/0fI6TZmfiqU/mqdefault.jpg",
              "width": 320,
              "height": 180
            },
            "high": {
              "url": "https://i.ytimg.com/vi/0fI6TZmfiqU/hqdefault.jpg",
              "width": 480,
              "height": 360
            }
          },
          "channelTitle": "NBA",
          "liveBroadcastContent": "none",
          "publishTime": "2021-04-24T01:55:33Z"
        }
      },
      {
        "kind": "youtube#searchResult",
        "etag": "mYFcD5-y8Tsv6r69DqW2IoeGS1k",
        "id": {
          "kind": "youtube#video",
          "videoId": "NAIPb5x21vs"
        },
        "snippet": {
          "publishedAt": "2021-03-20T02:20:20Z",
          "channelId": "UCWJ2lWNubArHWmf3FIHbfcQ",
          "title": "NETS at MAGIC | FULL GAME HIGHLIGHTS | March 19, 2021",
          "description": "NETS at MAGIC | FULL GAME HIGHLIGHTS | March 19, 2021 The Orlando Magic defeated the Brooklyn Nets, 121-113. Aaron Gordon led the Magic with a ...",
          "thumbnails": {
            "default": {
              "url": "https://i.ytimg.com/vi/NAIPb5x21vs/default.jpg",
              "width": 120,
              "height": 90
            },
            "medium": {
              "url": "https://i.ytimg.com/vi/NAIPb5x21vs/mqdefault.jpg",
              "width": 320,
              "height": 180
            },
            "high": {
              "url": "https://i.ytimg.com/vi/NAIPb5x21vs/hqdefault.jpg",
              "width": 480,
              "height": 360
            }
          },
          "channelTitle": "NBA",
          "liveBroadcastContent": "none",
          "publishTime": "2021-03-20T02:20:20Z"
        }
      },
      {
        "kind": "youtube#searchResult",
        "etag": "1qmZShXRfM8RgKzYzGPeJC4K_xc",
        "id": {
          "kind": "youtube#video",
          "videoId": "wnLSe8DUx60"
        },
        "snippet": {
          "publishedAt": "2021-03-26T04:50:12Z",
          "channelId": "UCWJ2lWNubArHWmf3FIHbfcQ",
          "title": "76ERS at LAKERS | FULL GAME HIGHLIGHTS | March 25, 2021",
          "description": "76ERS at LAKERS | FULL GAME HIGHLIGHTS | March 25, 2021 The Philadelphia 76ers defeated the Los Angeles Lakers, 109-101. Danny Green recorded 28 ...",
          "thumbnails": {
            "default": {
              "url": "https://i.ytimg.com/vi/wnLSe8DUx60/default.jpg",
              "width": 120,
              "height": 90
            },
            "medium": {
              "url": "https://i.ytimg.com/vi/wnLSe8DUx60/mqdefault.jpg",
              "width": 320,
              "height": 180
            },
            "high": {
              "url": "https://i.ytimg.com/vi/wnLSe8DUx60/hqdefault.jpg",
              "width": 480,
              "height": 360
            }
          },
          "channelTitle": "NBA",
          "liveBroadcastContent": "none",
          "publishTime": "2021-03-26T04:50:12Z"
        }
      },
      {
        "kind": "youtube#searchResult",
        "etag": "Uky48ggvsjdoF4QlyV4zV9u_B38",
        "id": {
          "kind": "youtube#video",
          "videoId": "LPlyp6uStxI"
        },
        "snippet": {
          "publishedAt": "2021-03-17T04:58:22Z",
          "channelId": "UCWJ2lWNubArHWmf3FIHbfcQ",
          "title": "TIMBERWOLVES at LAKERS | FULL GAME HIGHLIGHTS | March 16, 2021",
          "description": "TIMBERWOLVES at LAKERS | FULL GAME HIGHLIGHTS | March 16, 2021 The Los Angeles Lakers defeated the Minnesota Timberwolves, 137-121. LeBron ...",
          "thumbnails": {
            "default": {
              "url": "https://i.ytimg.com/vi/LPlyp6uStxI/default.jpg",
              "width": 120,
              "height": 90
            },
            "medium": {
              "url": "https://i.ytimg.com/vi/LPlyp6uStxI/mqdefault.jpg",
              "width": 320,
              "height": 180
            },
            "high": {
              "url": "https://i.ytimg.com/vi/LPlyp6uStxI/hqdefault.jpg",
              "width": 480,
              "height": 360
            }
          },
          "channelTitle": "NBA",
          "liveBroadcastContent": "none",
          "publishTime": "2021-03-17T04:58:22Z"
        }
      },
      {
        "kind": "youtube#searchResult",
        "etag": "VCdgR6EfH41_dlGGChogBy4BaYw",
        "id": {
          "kind": "youtube#video",
          "videoId": "4vcACh6XsJk"
        },
        "snippet": {
          "publishedAt": "2021-03-18T02:29:58Z",
          "channelId": "UCWJ2lWNubArHWmf3FIHbfcQ",
          "title": "WARRIORS at ROCKETS | FULL GAME HIGHLIGHTS | March 17, 2021",
          "description": "WARRIORS at ROCKETS | FULL GAME HIGHLIGHTS | March 17, 2021 The Golden State Warriors defeated the Houston Rockets, 108-94. Draymond Green ...",
          "thumbnails": {
            "default": {
              "url": "https://i.ytimg.com/vi/4vcACh6XsJk/default.jpg",
              "width": 120,
              "height": 90
            },
            "medium": {
              "url": "https://i.ytimg.com/vi/4vcACh6XsJk/mqdefault.jpg",
              "width": 320,
              "height": 180
            },
            "high": {
              "url": "https://i.ytimg.com/vi/4vcACh6XsJk/hqdefault.jpg",
              "width": 480,
              "height": 360
            }
          },
          "channelTitle": "NBA",
          "liveBroadcastContent": "none",
          "publishTime": "2021-03-18T02:29:58Z"
        }
      },
      {
        "kind": "youtube#searchResult",
        "etag": "FKhmk_FczI3xsSvi2qDMRNIR3tQ",
        "id": {
          "kind": "youtube#video",
          "videoId": "127F8HCyHwY"
        },
        "snippet": {
          "publishedAt": "2021-04-26T01:35:37Z",
          "channelId": "UCWJ2lWNubArHWmf3FIHbfcQ",
          "title": "CAVALIERS at WIZARDS | FULL GAME HIGHLIGHTS | April 25, 2021",
          "description": "CAVALIERS at WIZARDS | FULL GAME HIGHLIGHTS | April 25, 2021 The Washington Wizards have now won 8 consecutive games as they defeated the ...",
          "thumbnails": {
            "default": {
              "url": "https://i.ytimg.com/vi/127F8HCyHwY/default.jpg",
              "width": 120,
              "height": 90
            },
            "medium": {
              "url": "https://i.ytimg.com/vi/127F8HCyHwY/mqdefault.jpg",
              "width": 320,
              "height": 180
            },
            "high": {
              "url": "https://i.ytimg.com/vi/127F8HCyHwY/hqdefault.jpg",
              "width": 480,
              "height": 360
            }
          },
          "channelTitle": "NBA",
          "liveBroadcastContent": "none",
          "publishTime": "2021-04-26T01:35:37Z"
        }
      },
      {
        "kind": "youtube#searchResult",
        "etag": "7wYprhO1Te-oGDRuQ7QIAxV_nRo",
        "id": {
          "kind": "youtube#video",
          "videoId": "jLsAAKGS__o"
        },
        "snippet": {
          "publishedAt": "2021-04-17T02:49:48Z",
          "channelId": "UCWJ2lWNubArHWmf3FIHbfcQ",
          "title": "TRAIL BLAZERS at SPURS | FULL GAME HIGHLIGHTS | April 16, 2021",
          "description": "TRAIL BLAZERS at SPURS | FULL GAME HIGHLIGHTS | April 16, 2021 The Portland Trail Blazers defeated the San Antonio Spurs, 107-106. CJ McCollum led ...",
          "thumbnails": {
            "default": {
              "url": "https://i.ytimg.com/vi/jLsAAKGS__o/default.jpg",
              "width": 120,
              "height": 90
            },
            "medium": {
              "url": "https://i.ytimg.com/vi/jLsAAKGS__o/mqdefault.jpg",
              "width": 320,
              "height": 180
            },
            "high": {
              "url": "https://i.ytimg.com/vi/jLsAAKGS__o/hqdefault.jpg",
              "width": 480,
              "height": 360
            }
          },
          "channelTitle": "NBA",
          "liveBroadcastContent": "none",
          "publishTime": "2021-04-17T02:49:48Z"
        }
      },
      {
        "kind": "youtube#searchResult",
        "etag": "XKvEE99ETU_6bieBXvugWsyJUEA",
        "id": {
          "kind": "youtube#video",
          "videoId": "dgfP0H779n8"
        },
        "snippet": {
          "publishedAt": "2021-04-16T21:33:28Z",
          "channelId": "UCWJ2lWNubArHWmf3FIHbfcQ",
          "title": "PACERS at JAZZ | FULL GAME HIGHLIGHTS | April 16, 2021",
          "description": "PACERS at JAZZ | FULL GAME HIGHLIGHTS | April 16, 2021 The Utah Jazz defeated the Indiana Pacers, 119-111, Utah's 2nd consecutive 17-point comeback ...",
          "thumbnails": {
            "default": {
              "url": "https://i.ytimg.com/vi/dgfP0H779n8/default.jpg",
              "width": 120,
              "height": 90
            },
            "medium": {
              "url": "https://i.ytimg.com/vi/dgfP0H779n8/mqdefault.jpg",
              "width": 320,
              "height": 180
            },
            "high": {
              "url": "https://i.ytimg.com/vi/dgfP0H779n8/hqdefault.jpg",
              "width": 480,
              "height": 360
            }
          },
          "channelTitle": "NBA",
          "liveBroadcastContent": "none",
          "publishTime": "2021-04-16T21:33:28Z"
        }
      },
      {
        "kind": "youtube#searchResult",
        "etag": "2LsX8-gCLlE8Du75qN5PIRmvNRM",
        "id": {
          "kind": "youtube#video",
          "videoId": "GXd9i-QJpEw"
        },
        "snippet": {
          "publishedAt": "2021-04-02T04:37:38Z",
          "channelId": "UCWJ2lWNubArHWmf3FIHbfcQ",
          "title": "NUGGETS at CLIPPERS | FULL GAME HIGHLIGHTS | April 1, 2021",
          "description": "NUGGETS at CLIPPERS | FULL GAME HIGHLIGHTS | April 1, 2021 The Denver Nuggets defeated the LA Clippers, 101-94. Jamal Murray recorded 23 PTS, ...",
          "thumbnails": {
            "default": {
              "url": "https://i.ytimg.com/vi/GXd9i-QJpEw/default.jpg",
              "width": 120,
              "height": 90
            },
            "medium": {
              "url": "https://i.ytimg.com/vi/GXd9i-QJpEw/mqdefault.jpg",
              "width": 320,
              "height": 180
            },
            "high": {
              "url": "https://i.ytimg.com/vi/GXd9i-QJpEw/hqdefault.jpg",
              "width": 480,
              "height": 360
            }
          },
          "channelTitle": "NBA",
          "liveBroadcastContent": "none",
          "publishTime": "2021-04-02T04:37:38Z"
        }
      },
      {
        "kind": "youtube#searchResult",
        "etag": "Qsp664JaK_p9_D50ZnJ4vVO9iso",
        "id": {
          "kind": "youtube#video",
          "videoId": "Wp1NOm3k0C8"
        },
        "snippet": {
          "publishedAt": "2021-02-17T05:54:05Z",
          "channelId": "UCWJ2lWNubArHWmf3FIHbfcQ",
          "title": "NETS at SUNS | FULL GAME HIGHLIGHTS | February 16, 2021",
          "description": "NETS at SUNS | FULL GAME HIGHLIGHTS | February 16, 2021 The Brooklyn Nets overcame a 24-point deficit to defeat the Phoenix Suns, 128-124. James ...",
          "thumbnails": {
            "default": {
              "url": "https://i.ytimg.com/vi/Wp1NOm3k0C8/default.jpg",
              "width": 120,
              "height": 90
            },
            "medium": {
              "url": "https://i.ytimg.com/vi/Wp1NOm3k0C8/mqdefault.jpg",
              "width": 320,
              "height": 180
            },
            "high": {
              "url": "https://i.ytimg.com/vi/Wp1NOm3k0C8/hqdefault.jpg",
              "width": 480,
              "height": 360
            }
          },
          "channelTitle": "NBA",
          "liveBroadcastContent": "none",
          "publishTime": "2021-02-17T05:54:05Z"
        }
      },
      {
        "kind": "youtube#searchResult",
        "etag": "HT_xgkgjKkuUe7AUWa4Daz6vEzA",
        "id": {
          "kind": "youtube#video",
          "videoId": "PDswNb56b8s"
        },
        "snippet": {
          "publishedAt": "2021-03-14T02:26:17Z",
          "channelId": "UCWJ2lWNubArHWmf3FIHbfcQ",
          "title": "PISTONS at NETS | FULL GAME HIGHLIGHTS | March 13, 2021",
          "description": "PISTONS at NETS | FULL GAME HIGHLIGHTS | March 13, 2021 The Brooklyn Nets defeated the Detroit Pistons, 100-95. James Harden led the way for the Nets ...",
          "thumbnails": {
            "default": {
              "url": "https://i.ytimg.com/vi/PDswNb56b8s/default.jpg",
              "width": 120,
              "height": 90
            },
            "medium": {
              "url": "https://i.ytimg.com/vi/PDswNb56b8s/mqdefault.jpg",
              "width": 320,
              "height": 180
            },
            "high": {
              "url": "https://i.ytimg.com/vi/PDswNb56b8s/hqdefault.jpg",
              "width": 480,
              "height": 360
            }
          },
          "channelTitle": "NBA",
          "liveBroadcastContent": "none",
          "publishTime": "2021-03-14T02:26:17Z"
        }
      },
      {
        "kind": "youtube#searchResult",
        "etag": "GmM2ZGXg9I68IeYLmvS36lPE-pM",
        "id": {
          "kind": "youtube#video",
          "videoId": "rLLdM_Kj_9A"
        },
        "snippet": {
          "publishedAt": "2021-04-18T07:19:41Z",
          "channelId": "UCWJ2lWNubArHWmf3FIHbfcQ",
          "title": "NBA Top 10 Plays Of The Night | April 17, 2021",
          "description": "Check out the top 10 plays of the night from April 17 featuring Dillon Brooks, Jayson Tatum, Stephen Curry and MORE! Subscribe to the NBA: ...",
          "thumbnails": {
            "default": {
              "url": "https://i.ytimg.com/vi/rLLdM_Kj_9A/default.jpg",
              "width": 120,
              "height": 90
            },
            "medium": {
              "url": "https://i.ytimg.com/vi/rLLdM_Kj_9A/mqdefault.jpg",
              "width": 320,
              "height": 180
            },
            "high": {
              "url": "https://i.ytimg.com/vi/rLLdM_Kj_9A/hqdefault.jpg",
              "width": 480,
              "height": 360
            }
          },
          "channelTitle": "NBA",
          "liveBroadcastContent": "none",
          "publishTime": "2021-04-18T07:19:41Z"
        }
      },
      {
        "kind": "youtube#searchResult",
        "etag": "n8m-d0ximRkp8q7-qCxehz_D62c",
        "id": {
          "kind": "youtube#video",
          "videoId": "SRhsR7Ly22I"
        },
        "snippet": {
          "publishedAt": "2021-03-20T21:55:34Z",
          "channelId": "UCWJ2lWNubArHWmf3FIHbfcQ",
          "title": "HAWKS at LAKERS | FULL GAME HIGHLIGHTS | March 20, 2021",
          "description": "HAWKS at LAKERS | FULL GAME HIGHLIGHTS | March 20, 2021 The Atlanta Hawks defeated the Los Angeles Lakers, 99-94, winning their 8th consecutive ...",
          "thumbnails": {
            "default": {
              "url": "https://i.ytimg.com/vi/SRhsR7Ly22I/default.jpg",
              "width": 120,
              "height": 90
            },
            "medium": {
              "url": "https://i.ytimg.com/vi/SRhsR7Ly22I/mqdefault.jpg",
              "width": 320,
              "height": 180
            },
            "high": {
              "url": "https://i.ytimg.com/vi/SRhsR7Ly22I/hqdefault.jpg",
              "width": 480,
              "height": 360
            }
          },
          "channelTitle": "NBA",
          "liveBroadcastContent": "none",
          "publishTime": "2021-03-20T21:55:34Z"
        }
      },
      {
        "kind": "youtube#searchResult",
        "etag": "vIBuAPMJVOEZ5litospFGmyMTqg",
        "id": {
          "kind": "youtube#video",
          "videoId": "yjTEtd9LonA"
        },
        "snippet": {
          "publishedAt": "2021-04-20T01:59:49Z",
          "channelId": "UCWJ2lWNubArHWmf3FIHbfcQ",
          "title": "BULLS at CELTICS | FULL GAME HIGHLIGHTS | April 19, 2021",
          "description": "BULLS at CELTICS | FULL GAME HIGHLIGHTS | April 19, 2021 The Chicago Bulls defeated the Boston Celtics, 102-96. Nikola Vucevic led the Bulls with 29 ...",
          "thumbnails": {
            "default": {
              "url": "https://i.ytimg.com/vi/yjTEtd9LonA/default.jpg",
              "width": 120,
              "height": 90
            },
            "medium": {
              "url": "https://i.ytimg.com/vi/yjTEtd9LonA/mqdefault.jpg",
              "width": 320,
              "height": 180
            },
            "high": {
              "url": "https://i.ytimg.com/vi/yjTEtd9LonA/hqdefault.jpg",
              "width": 480,
              "height": 360
            }
          },
          "channelTitle": "NBA",
          "liveBroadcastContent": "none",
          "publishTime": "2021-04-20T01:59:49Z"
        }
      },
      {
        "kind": "youtube#searchResult",
        "etag": "I2knHpxsIJPehEUGzRZP_9oYqW0",
        "id": {
          "kind": "youtube#video",
          "videoId": "t_r2EYxoZkg"
        },
        "snippet": {
          "publishedAt": "2021-04-19T18:00:10Z",
          "channelId": "UCWJ2lWNubArHWmf3FIHbfcQ",
          "title": "Top PLAYS Of The Week | Week 17",
          "description": "Relive the top PLAYS from Week 17 in the NBA! Drop your favorite play in the comments ⤵ Subscribe to the NBA: https://on.nba.com/2JX5gSN Full Game ...",
          "thumbnails": {
            "default": {
              "url": "https://i.ytimg.com/vi/t_r2EYxoZkg/default.jpg",
              "width": 120,
              "height": 90
            },
            "medium": {
              "url": "https://i.ytimg.com/vi/t_r2EYxoZkg/mqdefault.jpg",
              "width": 320,
              "height": 180
            },
            "high": {
              "url": "https://i.ytimg.com/vi/t_r2EYxoZkg/hqdefault.jpg",
              "width": 480,
              "height": 360
            }
          },
          "channelTitle": "NBA",
          "liveBroadcastContent": "none",
          "publishTime": "2021-04-19T18:00:10Z"
        }
      },
      {
        "kind": "youtube#searchResult",
        "etag": "_h7J9BYxn6IN-vvgkIDmJ-eJIXs",
        "id": {
          "kind": "youtube#video",
          "videoId": "TVcxPw1cKs0"
        },
        "snippet": {
          "publishedAt": "2021-03-28T03:45:55Z",
          "channelId": "UCWJ2lWNubArHWmf3FIHbfcQ",
          "title": "MAVERICKS at PELICANS | FULL GAME HIGHLIGHTS | March 27, 2021",
          "description": "MAVERICKS at PELICANS | FULL GAME HIGHLIGHTS | March 27, 2021 The New Orleans Pelicans defeated the Dallas Mavericks, 112-103. Zion Williamson ...",
          "thumbnails": {
            "default": {
              "url": "https://i.ytimg.com/vi/TVcxPw1cKs0/default.jpg",
              "width": 120,
              "height": 90
            },
            "medium": {
              "url": "https://i.ytimg.com/vi/TVcxPw1cKs0/mqdefault.jpg",
              "width": 320,
              "height": 180
            },
            "high": {
              "url": "https://i.ytimg.com/vi/TVcxPw1cKs0/hqdefault.jpg",
              "width": 480,
              "height": 360
            }
          },
          "channelTitle": "NBA",
          "liveBroadcastContent": "none",
          "publishTime": "2021-03-28T03:45:55Z"
        }
      },
      {
        "kind": "youtube#searchResult",
        "etag": "KjrAVMuUdChTuKKhNZPdbXK2ep4",
        "id": {
          "kind": "youtube#video",
          "videoId": "FLXAMEiYqf8"
        },
        "snippet": {
          "publishedAt": "2021-04-12T04:20:08Z",
          "channelId": "UCWJ2lWNubArHWmf3FIHbfcQ",
          "title": "HEAT at BLAZERS | FULL GAME HIGHLIGHTS | April 11, 2021",
          "description": "HEAT at BLAZERS | FULL GAME HIGHLIGHTS | April 11, 2021 The Miami Heat defeated the Portland Trail Blazers, 107-98. Jimmy Butler led the Heat with 20 ...",
          "thumbnails": {
            "default": {
              "url": "https://i.ytimg.com/vi/FLXAMEiYqf8/default.jpg",
              "width": 120,
              "height": 90
            },
            "medium": {
              "url": "https://i.ytimg.com/vi/FLXAMEiYqf8/mqdefault.jpg",
              "width": 320,
              "height": 180
            },
            "high": {
              "url": "https://i.ytimg.com/vi/FLXAMEiYqf8/hqdefault.jpg",
              "width": 480,
              "height": 360
            }
          },
          "channelTitle": "NBA",
          "liveBroadcastContent": "none",
          "publishTime": "2021-04-12T04:20:08Z"
        }
      },
      {
        "kind": "youtube#searchResult",
        "etag": "HFxAl1853jhuloJMTn_hT7ZDkDw",
        "id": {
          "kind": "youtube#video",
          "videoId": "PXex-lXEk_A"
        },
        "snippet": {
          "publishedAt": "2021-04-09T03:32:35Z",
          "channelId": "UCWJ2lWNubArHWmf3FIHbfcQ",
          "title": "BUCKS at MAVERICKS | FULL GAME HIGHLIGHTS | April 8, 2021",
          "description": "BUCKS at MAVERICKS | FULL GAME HIGHLIGHTS | April 8, 2021 After outscoring the Milwaukee Bucks, 36-17, in the 4th quarter, the Dallas Mavericks earned ...",
          "thumbnails": {
            "default": {
              "url": "https://i.ytimg.com/vi/PXex-lXEk_A/default.jpg",
              "width": 120,
              "height": 90
            },
            "medium": {
              "url": "https://i.ytimg.com/vi/PXex-lXEk_A/mqdefault.jpg",
              "width": 320,
              "height": 180
            },
            "high": {
              "url": "https://i.ytimg.com/vi/PXex-lXEk_A/hqdefault.jpg",
              "width": 480,
              "height": 360
            }
          },
          "channelTitle": "NBA",
          "liveBroadcastContent": "none",
          "publishTime": "2021-04-09T03:32:35Z"
        }
      },
      {
        "kind": "youtube#searchResult",
        "etag": "SjPPCjDoMWpUyU5D4Awmvtn23ac",
        "id": {
          "kind": "youtube#video",
          "videoId": "ww-i9bztHdI"
        },
        "snippet": {
          "publishedAt": "2021-03-18T01:42:34Z",
          "channelId": "UCWJ2lWNubArHWmf3FIHbfcQ",
          "title": "NETS at PACERS | FULL GAME HIGHLIGHTS | March 17, 2021",
          "description": "NETS at PACERS | FULL GAME HIGHLIGHTS | March 17, 2021 James Harden recorded 40 PTS, 10 REB and 15 AST for the Brooklyn Nets as they defeated the ...",
          "thumbnails": {
            "default": {
              "url": "https://i.ytimg.com/vi/ww-i9bztHdI/default.jpg",
              "width": 120,
              "height": 90
            },
            "medium": {
              "url": "https://i.ytimg.com/vi/ww-i9bztHdI/mqdefault.jpg",
              "width": 320,
              "height": 180
            },
            "high": {
              "url": "https://i.ytimg.com/vi/ww-i9bztHdI/hqdefault.jpg",
              "width": 480,
              "height": 360
            }
          },
          "channelTitle": "NBA",
          "liveBroadcastContent": "none",
          "publishTime": "2021-03-18T01:42:34Z"
        }
      },
      {
        "kind": "youtube#searchResult",
        "etag": "2VjDPVeXGJTVHGxapmPxXmbC5MQ",
        "id": {
          "kind": "youtube#video",
          "videoId": "bZpzEeuZHqI"
        },
        "snippet": {
          "publishedAt": "2021-02-03T03:12:34Z",
          "channelId": "UCWJ2lWNubArHWmf3FIHbfcQ",
          "title": "CLIPPERS at NETS | FULL GAME HIGHLIGHTS | February 2, 2021",
          "description": "CLIPPERS at NETS | FULL GAME HIGHLIGHTS | February 2, 2021 Kyrie Irving recorded a season-high 39 PTS for the Brooklyn Nets as they defeated the LA ...",
          "thumbnails": {
            "default": {
              "url": "https://i.ytimg.com/vi/bZpzEeuZHqI/default.jpg",
              "width": 120,
              "height": 90
            },
            "medium": {
              "url": "https://i.ytimg.com/vi/bZpzEeuZHqI/mqdefault.jpg",
              "width": 320,
              "height": 180
            },
            "high": {
              "url": "https://i.ytimg.com/vi/bZpzEeuZHqI/hqdefault.jpg",
              "width": 480,
              "height": 360
            }
          },
          "channelTitle": "NBA",
          "liveBroadcastContent": "none",
          "publishTime": "2021-02-03T03:12:34Z"
        }
      },
      {
        "kind": "youtube#searchResult",
        "etag": "GY4BCaDd9gR2fomkKemLpEdAOd0",
        "id": {
          "kind": "youtube#video",
          "videoId": "GAC6S213T3U"
        },
        "snippet": {
          "publishedAt": "2021-03-27T02:01:02Z",
          "channelId": "UCWJ2lWNubArHWmf3FIHbfcQ",
          "title": "NETS at PISTONS | FULL GAME HIGHLIGHTS | March 26, 2021",
          "description": "NETS at PISTONS | FULL GAME HIGHLIGHTS | March 26, 2021 The Brooklyn Nets defeated the Detroit Pistons, 113-111. James Harden (44 PTS, 14 REB, ...",
          "thumbnails": {
            "default": {
              "url": "https://i.ytimg.com/vi/GAC6S213T3U/default.jpg",
              "width": 120,
              "height": 90
            },
            "medium": {
              "url": "https://i.ytimg.com/vi/GAC6S213T3U/mqdefault.jpg",
              "width": 320,
              "height": 180
            },
            "high": {
              "url": "https://i.ytimg.com/vi/GAC6S213T3U/hqdefault.jpg",
              "width": 480,
              "height": 360
            }
          },
          "channelTitle": "NBA",
          "liveBroadcastContent": "none",
          "publishTime": "2021-03-27T02:01:02Z"
        }
      },
      {
        "kind": "youtube#searchResult",
        "etag": "8z3_Afsjp7tGI0RbUrKvEYM5NDE",
        "id": {
          "kind": "youtube#video",
          "videoId": "QriUh3kIETY"
        },
        "snippet": {
          "publishedAt": "2021-01-19T05:50:27Z",
          "channelId": "UCWJ2lWNubArHWmf3FIHbfcQ",
          "title": "WARRIORS at LAKERS | FULL GAME HIGHLIGHTS | January 18, 2021",
          "description": "WARRIORS at LAKERS | FULL GAME HIGHLIGHTS | January 18, 2021 After trailing by as many as 19 points, the Golden State Warriors defeated the Los ...",
          "thumbnails": {
            "default": {
              "url": "https://i.ytimg.com/vi/QriUh3kIETY/default.jpg",
              "width": 120,
              "height": 90
            },
            "medium": {
              "url": "https://i.ytimg.com/vi/QriUh3kIETY/mqdefault.jpg",
              "width": 320,
              "height": 180
            },
            "high": {
              "url": "https://i.ytimg.com/vi/QriUh3kIETY/hqdefault.jpg",
              "width": 480,
              "height": 360
            }
          },
          "channelTitle": "NBA",
          "liveBroadcastContent": "none",
          "publishTime": "2021-01-19T05:50:27Z"
        }
      },
      {
        "kind": "youtube#searchResult",
        "etag": "hSFdT9fCkPe1I2WWpXrjgWTyIQ0",
        "id": {
          "kind": "youtube#video",
          "videoId": "JqJVJceDZhU"
        },
        "snippet": {
          "publishedAt": "2021-01-19T03:08:07Z",
          "channelId": "UCWJ2lWNubArHWmf3FIHbfcQ",
          "title": "BUCKS at NETS | FULL GAME HIGHLIGHTS | January 18, 2021",
          "description": "BUCKS at NETS | FULL GAME HIGHLIGHTS | January 18, 2021 The Brooklyn Nets defeated the Milwaukee Bucks, 125-123. James Harden (34 PTS, 6 REB, ...",
          "thumbnails": {
            "default": {
              "url": "https://i.ytimg.com/vi/JqJVJceDZhU/default.jpg",
              "width": 120,
              "height": 90
            },
            "medium": {
              "url": "https://i.ytimg.com/vi/JqJVJceDZhU/mqdefault.jpg",
              "width": 320,
              "height": 180
            },
            "high": {
              "url": "https://i.ytimg.com/vi/JqJVJceDZhU/hqdefault.jpg",
              "width": 480,
              "height": 360
            }
          },
          "channelTitle": "NBA",
          "liveBroadcastContent": "none",
          "publishTime": "2021-01-19T03:08:07Z"
        }
      },
      {
        "kind": "youtube#searchResult",
        "etag": "_AHjCOxlMY8mUwHQkcs4Oi8uk4U",
        "id": {
          "kind": "youtube#video",
          "videoId": "E3pVlq-Isy0"
        },
        "snippet": {
          "publishedAt": "2021-04-13T03:44:57Z",
          "channelId": "UCWJ2lWNubArHWmf3FIHbfcQ",
          "title": "WIZARDS at JAZZ | FULL GAME HIGHLIGHTS | April 12, 2021",
          "description": "WIZARDS at JAZZ | FULL GAME HIGHLIGHTS | April 12, 2021 The Washington Wizards defeated the Utah Jazz, 125-121, snapping Utah's franchise record ...",
          "thumbnails": {
            "default": {
              "url": "https://i.ytimg.com/vi/E3pVlq-Isy0/default.jpg",
              "width": 120,
              "height": 90
            },
            "medium": {
              "url": "https://i.ytimg.com/vi/E3pVlq-Isy0/mqdefault.jpg",
              "width": 320,
              "height": 180
            },
            "high": {
              "url": "https://i.ytimg.com/vi/E3pVlq-Isy0/hqdefault.jpg",
              "width": 480,
              "height": 360
            }
          },
          "channelTitle": "NBA",
          "liveBroadcastContent": "none",
          "publishTime": "2021-04-13T03:44:57Z"
        }
      },
      {
        "kind": "youtube#searchResult",
        "etag": "wopPp2kOgq0t9pESTbwqJEUftQw",
        "id": {
          "kind": "youtube#video",
          "videoId": "ce0qJYJ2JhM"
        },
        "snippet": {
          "publishedAt": "2021-03-17T02:07:47Z",
          "channelId": "UCWJ2lWNubArHWmf3FIHbfcQ",
          "title": "JAZZ at CELTICS | FULL GAME HIGHLIGHTS | March 16, 2021",
          "description": "JAZZ at CELTICS | FULL GAME HIGHLIGHTS | March 16, 2021 The Utah Jazz defeated the Boston Celtics, 117-109. Donovan Mitchell led the Jazz with 21 PTS ...",
          "thumbnails": {
            "default": {
              "url": "https://i.ytimg.com/vi/ce0qJYJ2JhM/default.jpg",
              "width": 120,
              "height": 90
            },
            "medium": {
              "url": "https://i.ytimg.com/vi/ce0qJYJ2JhM/mqdefault.jpg",
              "width": 320,
              "height": 180
            },
            "high": {
              "url": "https://i.ytimg.com/vi/ce0qJYJ2JhM/hqdefault.jpg",
              "width": 480,
              "height": 360
            }
          },
          "channelTitle": "NBA",
          "liveBroadcastContent": "none",
          "publishTime": "2021-03-17T02:07:47Z"
        }
      },
      {
        "kind": "youtube#searchResult",
        "etag": "94cwphgrohbfr-siS2osQ6rWkww",
        "id": {
          "kind": "youtube#video",
          "videoId": "nc6tILLMJ2A"
        },
        "snippet": {
          "publishedAt": "2021-04-13T06:29:04Z",
          "channelId": "UCWJ2lWNubArHWmf3FIHbfcQ",
          "title": "NBA Top 10 Plays Of The Night | April 12, 2021",
          "description": "Check out the top 10 plays of the night from April 12 featuring Miles Bridges, and MORE! 0:00\u200b\u200b\u200b\u200b\u200b - 10 | Keldon Johnson 0:09\u200b\u200b - 9 | Royce O'neal ...",
          "thumbnails": {
            "default": {
              "url": "https://i.ytimg.com/vi/nc6tILLMJ2A/default.jpg",
              "width": 120,
              "height": 90
            },
            "medium": {
              "url": "https://i.ytimg.com/vi/nc6tILLMJ2A/mqdefault.jpg",
              "width": 320,
              "height": 180
            },
            "high": {
              "url": "https://i.ytimg.com/vi/nc6tILLMJ2A/hqdefault.jpg",
              "width": 480,
              "height": 360
            }
          },
          "channelTitle": "NBA",
          "liveBroadcastContent": "none",
          "publishTime": "2021-04-13T06:29:04Z"
        }
      },
      {
        "kind": "youtube#searchResult",
        "etag": "CxJzajrqAkNprfiwL98oXdeatiM",
        "id": {
          "kind": "youtube#video",
          "videoId": "ZNF6oPOOyqk"
        },
        "snippet": {
          "publishedAt": "2021-03-27T05:06:02Z",
          "channelId": "UCWJ2lWNubArHWmf3FIHbfcQ",
          "title": "CAVALIERS at LAKERS | FULL GAME HIGHLIGHTS | March 26, 2021",
          "description": "CAVALIERS at LAKERS | FULL GAME HIGHLIGHTS | March 26, 2021 The Los Angeles Lakers defeated the Cleveland Cavaliers, 100-86. Montrezl Harrell led ...",
          "thumbnails": {
            "default": {
              "url": "https://i.ytimg.com/vi/ZNF6oPOOyqk/default.jpg",
              "width": 120,
              "height": 90
            },
            "medium": {
              "url": "https://i.ytimg.com/vi/ZNF6oPOOyqk/mqdefault.jpg",
              "width": 320,
              "height": 180
            },
            "high": {
              "url": "https://i.ytimg.com/vi/ZNF6oPOOyqk/hqdefault.jpg",
              "width": 480,
              "height": 360
            }
          },
          "channelTitle": "NBA",
          "liveBroadcastContent": "none",
          "publishTime": "2021-03-27T05:06:02Z"
        }
      },
      {
        "kind": "youtube#searchResult",
        "etag": "cwgOQErBzaYmDkM9-p-cnKeTK0s",
        "id": {
          "kind": "youtube#video",
          "videoId": "5kGKuBEGeI0"
        },
        "snippet": {
          "publishedAt": "2021-04-26T17:30:00Z",
          "channelId": "UCWJ2lWNubArHWmf3FIHbfcQ",
          "title": "TOP DUNKS From the Week! | Week 18",
          "description": "Take a look at the best DUNKS from Week 18 in the NBA! Drop your favorite dunk in the comments ⤵ Subscribe to the NBA: https://on.nba.com/2JX5gSN Full ...",
          "thumbnails": {
            "default": {
              "url": "https://i.ytimg.com/vi/5kGKuBEGeI0/default.jpg",
              "width": 120,
              "height": 90
            },
            "medium": {
              "url": "https://i.ytimg.com/vi/5kGKuBEGeI0/mqdefault.jpg",
              "width": 320,
              "height": 180
            },
            "high": {
              "url": "https://i.ytimg.com/vi/5kGKuBEGeI0/hqdefault.jpg",
              "width": 480,
              "height": 360
            }
          },
          "channelTitle": "NBA",
          "liveBroadcastContent": "none",
          "publishTime": "2021-04-26T17:30:00Z"
        }
      },
      {
        "kind": "youtube#searchResult",
        "etag": "UQETGtoclJMn_DpdyENTWDnBPaQ",
        "id": {
          "kind": "youtube#video",
          "videoId": "-w9OGzoeen4"
        },
        "snippet": {
          "publishedAt": "2021-01-09T03:11:09Z",
          "channelId": "UCWJ2lWNubArHWmf3FIHbfcQ",
          "title": "HORNETS at PELICANS | FULL GAME HIGHLIGHTS | January 8, 2021",
          "description": "HORNETS at PELICANS | FULL GAME HIGHLIGHTS | January 8, 2021 The Charlotte Hornets defeated the New Orleans Pelicans, 118-110. LaMelo Ball ...",
          "thumbnails": {
            "default": {
              "url": "https://i.ytimg.com/vi/-w9OGzoeen4/default.jpg",
              "width": 120,
              "height": 90
            },
            "medium": {
              "url": "https://i.ytimg.com/vi/-w9OGzoeen4/mqdefault.jpg",
              "width": 320,
              "height": 180
            },
            "high": {
              "url": "https://i.ytimg.com/vi/-w9OGzoeen4/hqdefault.jpg",
              "width": 480,
              "height": 360
            }
          },
          "channelTitle": "NBA",
          "liveBroadcastContent": "none",
          "publishTime": "2021-01-09T03:11:09Z"
        }
      },
      {
        "kind": "youtube#searchResult",
        "etag": "AYnwmJ_A3vdPPjvAwJlP5vyxVfI",
        "id": {
          "kind": "youtube#video",
          "videoId": "mCBLJXKGv-w"
        },
        "snippet": {
          "publishedAt": "2021-01-28T03:18:18Z",
          "channelId": "UCWJ2lWNubArHWmf3FIHbfcQ",
          "title": "NETS at HAWKS | FULL GAME HIGHLIGHTS | January 27, 2021",
          "description": "NETS at HAWKS | FULL GAME HIGHLIGHTS | January 27, 2021 James Harden (31 PTS, 8 REB, 15 AST) and Kevin Durant (32 PTS, 5 REB, 2 BLK) combined ...",
          "thumbnails": {
            "default": {
              "url": "https://i.ytimg.com/vi/mCBLJXKGv-w/default.jpg",
              "width": 120,
              "height": 90
            },
            "medium": {
              "url": "https://i.ytimg.com/vi/mCBLJXKGv-w/mqdefault.jpg",
              "width": 320,
              "height": 180
            },
            "high": {
              "url": "https://i.ytimg.com/vi/mCBLJXKGv-w/hqdefault.jpg",
              "width": 480,
              "height": 360
            }
          },
          "channelTitle": "NBA",
          "liveBroadcastContent": "none",
          "publishTime": "2021-01-28T03:18:18Z"
        }
      },
      {
        "kind": "youtube#searchResult",
        "etag": "hrOT7Nmj3QDdo-dV92dCRR_Ykcw",
        "id": {
          "kind": "youtube#video",
          "videoId": "xzHiLBUWcvg"
        },
        "snippet": {
          "publishedAt": "2021-04-11T06:35:24Z",
          "channelId": "UCWJ2lWNubArHWmf3FIHbfcQ",
          "title": "NBA Top 10 Plays Of The Night | April 10, 2021",
          "description": "Check out the top 10 plays of the night from April 10 featuring, Donovan Mitchell, De'aaron Fox and MORE! 0:00\u200b\u200b\u200b - 10 | Isaiah Hartenstein 0:15 - 9 | Derrick ...",
          "thumbnails": {
            "default": {
              "url": "https://i.ytimg.com/vi/xzHiLBUWcvg/default.jpg",
              "width": 120,
              "height": 90
            },
            "medium": {
              "url": "https://i.ytimg.com/vi/xzHiLBUWcvg/mqdefault.jpg",
              "width": 320,
              "height": 180
            },
            "high": {
              "url": "https://i.ytimg.com/vi/xzHiLBUWcvg/hqdefault.jpg",
              "width": 480,
              "height": 360
            }
          },
          "channelTitle": "NBA",
          "liveBroadcastContent": "none",
          "publishTime": "2021-04-11T06:35:24Z"
        }
      },
      {
        "kind": "youtube#searchResult",
        "etag": "_bh_DQglSCIicWuiHJFHTgnLtxY",
        "id": {
          "kind": "youtube#video",
          "videoId": "H6qUkj4I_xM"
        },
        "snippet": {
          "publishedAt": "2021-02-28T03:55:43Z",
          "channelId": "UCWJ2lWNubArHWmf3FIHbfcQ",
          "title": "MAVERICKS at NETS | FULL GAME HIGHLIGHTS | February 27, 2021",
          "description": "MAVERICKS at NETS | FULL GAME HIGHLIGHTS | February 27, 2021 The Dallas Mavericks defeated the Brooklyn Nets, 115-98, snapping Brooklyn's 8-game ...",
          "thumbnails": {
            "default": {
              "url": "https://i.ytimg.com/vi/H6qUkj4I_xM/default.jpg",
              "width": 120,
              "height": 90
            },
            "medium": {
              "url": "https://i.ytimg.com/vi/H6qUkj4I_xM/mqdefault.jpg",
              "width": 320,
              "height": 180
            },
            "high": {
              "url": "https://i.ytimg.com/vi/H6qUkj4I_xM/hqdefault.jpg",
              "width": 480,
              "height": 360
            }
          },
          "channelTitle": "NBA",
          "liveBroadcastContent": "none",
          "publishTime": "2021-02-28T03:55:43Z"
        }
      },
      {
        "kind": "youtube#searchResult",
        "etag": "GmXP89OxbW4-Yv2F_DlEo2acAhU",
        "id": {
          "kind": "youtube#video",
          "videoId": "pMAxRWiV0uw"
        },
        "snippet": {
          "publishedAt": "2021-04-04T01:25:17Z",
          "channelId": "UCWJ2lWNubArHWmf3FIHbfcQ",
          "title": "MAVERICKS at WIZARDS | FULL GAME HIGHLIGHTS | April 3, 2021",
          "description": "MAVERICKS at WIZARDS | FULL GAME HIGHLIGHTS | April 3, 2021 The Dallas Mavericks defeated the Washington Wizards, 109-87. Luka Doncic recorded 26 ...",
          "thumbnails": {
            "default": {
              "url": "https://i.ytimg.com/vi/pMAxRWiV0uw/default.jpg",
              "width": 120,
              "height": 90
            },
            "medium": {
              "url": "https://i.ytimg.com/vi/pMAxRWiV0uw/mqdefault.jpg",
              "width": 320,
              "height": 180
            },
            "high": {
              "url": "https://i.ytimg.com/vi/pMAxRWiV0uw/hqdefault.jpg",
              "width": 480,
              "height": 360
            }
          },
          "channelTitle": "NBA",
          "liveBroadcastContent": "none",
          "publishTime": "2021-04-04T01:25:17Z"
        }
      },
      {
        "kind": "youtube#searchResult",
        "etag": "P5RYcp-UiMF8xy8i-mfXsl_aIPs",
        "id": {
          "kind": "youtube#video",
          "videoId": "I6pdsGTDC7U"
        },
        "snippet": {
          "publishedAt": "2021-03-12T05:40:44Z",
          "channelId": "UCWJ2lWNubArHWmf3FIHbfcQ",
          "title": "WARRIORS at CLIPPERS | FULL GAME HIGHLIGHTS | March 11, 2021",
          "description": "WARRIORS at CLIPPERS | FULL GAME HIGHLIGHTS | March 11, 2021 Led by Kawhi Leonard's 28 PTS and 9 REB, the LA Clippers defeated the Golden State ...",
          "thumbnails": {
            "default": {
              "url": "https://i.ytimg.com/vi/I6pdsGTDC7U/default.jpg",
              "width": 120,
              "height": 90
            },
            "medium": {
              "url": "https://i.ytimg.com/vi/I6pdsGTDC7U/mqdefault.jpg",
              "width": 320,
              "height": 180
            },
            "high": {
              "url": "https://i.ytimg.com/vi/I6pdsGTDC7U/hqdefault.jpg",
              "width": 480,
              "height": 360
            }
          },
          "channelTitle": "NBA",
          "liveBroadcastContent": "none",
          "publishTime": "2021-03-12T05:40:44Z"
        }
      },
      {
        "kind": "youtube#searchResult",
        "etag": "sjnFwbKnkn3TFmoX9NlKXWkKcNc",
        "id": {
          "kind": "youtube#video",
          "videoId": "EE3k9EH0p6Y"
        },
        "snippet": {
          "publishedAt": "2021-01-06T03:31:40Z",
          "channelId": "UCWJ2lWNubArHWmf3FIHbfcQ",
          "title": "LOS ANGELES LAKERS at MEMPHIS GRIZZLIES | FULL GAME HIGHLIGHTS | JANUARY 5, 2021",
          "description": "LOS ANGELES LAKERS at MEMPHIS GRIZZLIES | FULL GAME HIGHLIGHTS | JANUARY 5, 2021 The Los Angeles Lakers defeated the Memphis Grizzlies, ...",
          "thumbnails": {
            "default": {
              "url": "https://i.ytimg.com/vi/EE3k9EH0p6Y/default.jpg",
              "width": 120,
              "height": 90
            },
            "medium": {
              "url": "https://i.ytimg.com/vi/EE3k9EH0p6Y/mqdefault.jpg",
              "width": 320,
              "height": 180
            },
            "high": {
              "url": "https://i.ytimg.com/vi/EE3k9EH0p6Y/hqdefault.jpg",
              "width": 480,
              "height": 360
            }
          },
          "channelTitle": "NBA",
          "liveBroadcastContent": "none",
          "publishTime": "2021-01-06T03:31:40Z"
        }
      },
      {
        "kind": "youtube#searchResult",
        "etag": "GCwzlUWvw05U1NK4T0M7q2wNqR4",
        "id": {
          "kind": "youtube#video",
          "videoId": "5ZobOpRvJFc"
        },
        "snippet": {
          "publishedAt": "2021-03-01T03:45:03Z",
          "channelId": "UCWJ2lWNubArHWmf3FIHbfcQ",
          "title": "WARRIORS at LAKERS | FULL GAME HIGHLIGHTS | February 28, 2021",
          "description": "WARRIORS at LAKERS | FULL GAME HIGHLIGHTS | February 28, 2021 The Los Angeles Lakers defeated the Golden State Warriors, 117-91. LeBron James ...",
          "thumbnails": {
            "default": {
              "url": "https://i.ytimg.com/vi/5ZobOpRvJFc/default.jpg",
              "width": 120,
              "height": 90
            },
            "medium": {
              "url": "https://i.ytimg.com/vi/5ZobOpRvJFc/mqdefault.jpg",
              "width": 320,
              "height": 180
            },
            "high": {
              "url": "https://i.ytimg.com/vi/5ZobOpRvJFc/hqdefault.jpg",
              "width": 480,
              "height": 360
            }
          },
          "channelTitle": "NBA",
          "liveBroadcastContent": "none",
          "publishTime": "2021-03-01T03:45:03Z"
        }
      }
    ]
  }
  